{
    "userId": "AQP506",
    "updateDate": null,
    "validationCode": "D-108",
    "validationMessage": "Duplicate parties found: At least one other customer already exists with the same information.",
    "matchFlag": true,
    "account": {
        
    },
    "accountMatch": [
        {
            "producerAssociationExists": true,
            "lenderFlag": false,
            "systemId": "19558187",
            "externalId": "0016C00000nt358192",
            "version": "1",
            "recordType": "Business",
            "accountName": "AmericanInsurance",
            "accountMatchType": "POSSIBLE",
            "partnerIdentifier": "AFI",
            "dissolvedFlag": true,
            "dissolvedDate": null,
            "formOfBusiness": "CORP",
            "formOfBusinessDescription": "",
            "jointVentureComment": "",
            "representativeName": "",
            "representativePosition": "",
            "greeting": "",
            "preferredContactMethod": "",
            "taxPayerIdType": "F",
            "mailingName": "",
            "employerIdentificationNumber": "Matches",
            "socialSecurityNumber": "",
            "lenderStatus": "",
            "deliveryPreference": "",
            "salutation": "",
            "firstName": "",
            "middleName": "",
            "lastName": "",
            "goesByName": "",
            "pronounciation": "",
            "familySuffix": "",
            "professionalSuffix": "",
            "professionalSuffixComment": "",
            "birthDate": null,
            "deceasedFlag": false,
            "deceasedDate": null,
            "gender": "",
            "maritalStatus": "",
            "employmentStatus": "",
            "employerName": "",
            "occupation": "",
            "occupationCategory": "",
            "alternateOccupation": "",
            "driversLicenseNumber": "",
            "driversLicenseState": "",
            "driversLicenseIssueMonth": "",
            "driversLicenseIssueYear": "",
            "primarySpokenLanguage": "",
            "secondarySpokenLanguage": "",
            "otherPrimarySpokenLanguage": "",
            "otherSecondarySpokenLanguage": "",
            "writtenLanguage": "",
            "address": {
                "records": [
                    {
                        "id": "",
                        "addressId": "",
                        "country": "USA",
                        "addressLine1": "717 NW 1st Ave",
                        "addressLine2": "",
                        "city": "Galva",
                        "state": "IL",
                        "postalCode": "61434",
                        "provinceTerritory": "",
                        "foreignPostalCode": "",
                        "purposeType": "PRM",
                        "usageType": "M"
                    }
                ]
            }
        },
        {
            "producerAssociationExists": true,
            "lenderFlag": false,
            "systemId": "19486343",
            "externalId": "0016C00000nt358192",
            "version": "1",
            "recordType": "Business",
            "accountName": "sagar",
            "accountMatchType": "POSSIBLE",
            "partnerIdentifier": "AFI",
            "dissolvedFlag": false,
            "dissolvedDate": null,
            "formOfBusiness": "JNTVNTR",
            "formOfBusinessDescription": "",
            "jointVentureComment": "Hello",
            "representativeName": "",
            "representativePosition": "",
            "greeting": "",
            "preferredContactMethod": "",
            "taxPayerIdType": "F",
            "mailingName": "",
            "employerIdentificationNumber": "Matches",
            "socialSecurityNumber": "",
            "lenderStatus": "",
            "deliveryPreference": "",
            "salutation": "",
            "firstName": "",
            "middleName": "",
            "lastName": "",
            "goesByName": "",
            "pronounciation": "",
            "familySuffix": "",
            "professionalSuffix": "",
            "professionalSuffixComment": "",
            "birthDate": null,
            "deceasedFlag": false,
            "deceasedDate": null,
            "gender": "",
            "maritalStatus": "",
            "employmentStatus": "",
            "employerName": "",
            "occupation": "",
            "occupationCategory": "",
            "alternateOccupation": "",
            "driversLicenseNumber": "",
            "driversLicenseState": "",
            "driversLicenseIssueMonth": "",
            "driversLicenseIssueYear": "",
            "primarySpokenLanguage": "",
            "secondarySpokenLanguage": "",
            "otherPrimarySpokenLanguage": "",
            "otherSecondarySpokenLanguage": "",
            "writtenLanguage": "",
            "address": {
                "records": [
                    {
                        "id": "",
                        "addressId": "",
                        "country": "IND",
                        "addressLine1": "987 nagar",
                        "addressLine2": "mnbv",
                        "city": "tenali",
                        "state": "",
                        "postalCode": "",
                        "provinceTerritory": "AP",
                        "foreignPostalCode": "09872",
                        "purposeType": "PRM",
                        "usageType": "M"
                    }
                ]
            }
        }
    ]
}